{
  "namn": "Alvin Skogström",
  "kandidaturer": [
    {
      "valtyp": "RF",
      "område": "Dalarna",
      "valkrets": "Region Dalarna",
      "parti": "Arbetarepartiet-Socialdemokraterna",
      "partiförkortning": "S",
      "ordning": "12",
      "kandidatnummer": "4814"
    },
    {
      "valtyp": "KF",
      "område": "Borlänge",
      "valkrets": "Borlänge",
      "parti": "Arbetarepartiet-Socialdemokraterna",
      "partiförkortning": "S",
      "ordning": "19",
      "kandidatnummer": "4814"
    }
  ]
}