{
  "namn": "Anita Övelius",
  "kandidaturer": [
    {
      "valtyp": "KF",
      "område": "Haninge",
      "valkrets": "Haninge Norra",
      "parti": "Arbetarepartiet-Socialdemokraterna",
      "partiförkortning": "S",
      "ordning": "58",
      "kandidatnummer": "18450"
    },
    {
      "valtyp": "KF",
      "område": "Haninge",
      "valkrets": "Haninge Södra",
      "parti": "Arbetarepartiet-Socialdemokraterna",
      "partiförkortning": "S",
      "ordning": "58",
      "kandidatnummer": "18450"
    }
  ]
}