{
  "namn": "Anja Johansson",
  "kandidaturer": [
    {
      "valtyp": "KF",
      "område": "Värnamo",
      "valkrets": "Värnamo",
      "parti": "Arbetarepartiet-Socialdemokraterna",
      "partiförkortning": "S",
      "ordning": "9",
      "kandidatnummer": "25104"
    },
    {
      "valtyp": "KF",
      "område": "Luleå",
      "valkrets": "Luleå",
      "parti": "Arbetarepartiet-Socialdemokraterna",
      "partiförkortning": "S",
      "ordning": "13",
      "kandidatnummer": "10956"
    }
  ]
}