{
  "namn": "Ann-Sofie Karlsson",
  "kandidaturer": [
    {
      "valtyp": "RF",
      "område": "Södermanland",
      "valkrets": "Region Södermanland",
      "parti": "Arbetarepartiet-Socialdemokraterna",
      "partiförkortning": "S",
      "ordning": "34",
      "kandidatnummer": "25598"
    },
    {
      "valtyp": "KF",
      "område": "Gnesta",
      "valkrets": "Gnesta",
      "parti": "Arbetarepartiet-Socialdemokraterna",
      "partiförkortning": "S",
      "ordning": "9",
      "kandidatnummer": "25598"
    }
  ]
}