{
  "namn": "Ayan Hashi",
  "kandidaturer": [
    {
      "valtyp": "RF",
      "område": "Östergötland",
      "valkrets": "Linköping",
      "parti": "Arbetarepartiet-Socialdemokraterna",
      "partiförkortning": "S",
      "ordning": "27",
      "kandidatnummer": "6706"
    },
    {
      "valtyp": "RF",
      "område": "Östergötland",
      "valkrets": "Norrköping",
      "parti": "Arbetarepartiet-Socialdemokraterna",
      "partiförkortning": "S",
      "ordning": "27",
      "kandidatnummer": "6706"
    },
    {
      "valtyp": "RF",
      "område": "Östergötland",
      "valkrets": "Kinda Åtvid Valdemarsvik Söderköping",
      "parti": "Arbetarepartiet-Socialdemokraterna",
      "partiförkortning": "S",
      "ordning": "27",
      "kandidatnummer": "6706"
    },
    {
      "valtyp": "RF",
      "område": "Östergötland",
      "valkrets": "Ödeshög Ydre Boxholm Mjölby Vadstena",
      "parti": "Arbetarepartiet-Socialdemokraterna",
      "partiförkortning": "S",
      "ordning": "27",
      "kandidatnummer": "6706"
    },
    {
      "valtyp": "RF",
      "område": "Östergötland",
      "valkrets": "Motala Finspång",
      "parti": "Arbetarepartiet-Socialdemokraterna",
      "partiförkortning": "S",
      "ordning": "27",
      "kandidatnummer": "6706"
    }
  ]
}