{
  "namn": "Bengt-Åke Nilsson",
  "kandidaturer": [
    {
      "valtyp": "RF",
      "område": "Västmanland",
      "valkrets": "Östra valkretsen",
      "parti": "Liberalerna (tidigare Folkpartiet)",
      "partiförkortning": "L",
      "ordning": "23",
      "kandidatnummer": "5583"
    },
    {
      "valtyp": "RF",
      "område": "Västmanland",
      "valkrets": "Västra valkretsen",
      "parti": "Liberalerna (tidigare Folkpartiet)",
      "partiförkortning": "L",
      "ordning": "23",
      "kandidatnummer": "5583"
    },
    {
      "valtyp": "KF",
      "område": "Västerås",
      "valkrets": "Västerås",
      "parti": "Liberalerna (tidigare Folkpartiet)",
      "partiförkortning": "L",
      "ordning": "23",
      "kandidatnummer": "5583"
    },
    {
      "valtyp": "KF",
      "område": "Hudiksvall",
      "valkrets": "Hudiksvall",
      "parti": "Centerpartiet",
      "partiförkortning": "C",
      "ordning": "12",
      "kandidatnummer": "36163"
    }
  ]
}