{
  "namn": "Berit Nilsson",
  "kandidaturer": [
    {
      "valtyp": "RF",
      "område": "Kronoberg",
      "valkrets": "Kronoberg",
      "parti": "Arbetarepartiet-Socialdemokraterna",
      "partiförkortning": "S",
      "ordning": "57",
      "kandidatnummer": "39380"
    },
    {
      "valtyp": "KF",
      "område": "Markaryd",
      "valkrets": "Markaryd",
      "parti": "Arbetarepartiet-Socialdemokraterna",
      "partiförkortning": "S",
      "ordning": "6",
      "kandidatnummer": "39380"
    }
  ]
}