{
  "namn": "Börje Söderström",
  "kandidaturer": [
    {
      "valtyp": "RF",
      "område": "Södermanland",
      "valkrets": "Region Södermanland",
      "parti": "Arbetarepartiet-Socialdemokraterna",
      "partiförkortning": "S",
      "ordning": "39",
      "kandidatnummer": "15134"
    },
    {
      "valtyp": "KF",
      "område": "Katrineholm",
      "valkrets": "Katrineholm",
      "parti": "Arbetarepartiet-Socialdemokraterna",
      "partiförkortning": "S",
      "ordning": "23",
      "kandidatnummer": "15134"
    }
  ]
}