{
  "namn": "Catharina Nord",
  "kandidaturer": [
    {
      "valtyp": "RD",
      "område": "Riket",
      "valkrets": "Kronobergs län",
      "parti": "Vänsterpartiet",
      "partiförkortning": "V",
      "ordning": "21",
      "kandidatnummer": "14474"
    },
    {
      "valtyp": "RF",
      "område": "Kronoberg",
      "valkrets": "Kronoberg",
      "parti": "Vänsterpartiet",
      "partiförkortning": "V",
      "ordning": "8",
      "kandidatnummer": "14474"
    },
    {
      "valtyp": "KF",
      "område": "Ljungby",
      "valkrets": "Ljungby",
      "parti": "Vänsterpartiet",
      "partiförkortning": "V",
      "ordning": "3",
      "kandidatnummer": "14474"
    }
  ]
}