{
  "namn": "Catrin Johansson",
  "kandidaturer": [
    {
      "valtyp": "RF",
      "område": "Uppsala",
      "valkrets": "Uppsala läns södra",
      "parti": "Arbetarepartiet-Socialdemokraterna",
      "partiförkortning": "S",
      "ordning": "23",
      "kandidatnummer": "6499"
    },
    {
      "valtyp": "RF",
      "område": "Uppsala",
      "valkrets": "Uppsala läns mellersta",
      "parti": "Arbetarepartiet-Socialdemokraterna",
      "partiförkortning": "S",
      "ordning": "23",
      "kandidatnummer": "6499"
    },
    {
      "valtyp": "RF",
      "område": "Uppsala",
      "valkrets": "Uppsala läns norra",
      "parti": "Arbetarepartiet-Socialdemokraterna",
      "partiförkortning": "S",
      "ordning": "23",
      "kandidatnummer": "6499"
    },
    {
      "valtyp": "KF",
      "område": "Enköping",
      "valkrets": "Enköping",
      "parti": "Liberalerna (tidigare Folkpartiet)",
      "partiförkortning": "L",
      "ordning": "5",
      "kandidatnummer": "19798"
    }
  ]
}