{
  "namn": "Christina Järnvik",
  "kandidaturer": [
    {
      "valtyp": "RF",
      "område": "Västra Götaland",
      "valkrets": "Göteborgs kommun",
      "parti": "Sverigedemokraterna",
      "partiförkortning": "SD",
      "ordning": "39",
      "kandidatnummer": "31078"
    },
    {
      "valtyp": "RF",
      "område": "Västra Götaland",
      "valkrets": "Västra Götalands läns västra",
      "parti": "Sverigedemokraterna",
      "partiförkortning": "SD",
      "ordning": "39",
      "kandidatnummer": "31078"
    },
    {
      "valtyp": "RF",
      "område": "Västra Götaland",
      "valkrets": "Västra Götalands läns norra",
      "parti": "Sverigedemokraterna",
      "partiförkortning": "SD",
      "ordning": "39",
      "kandidatnummer": "31078"
    },
    {
      "valtyp": "RF",
      "område": "Västra Götaland",
      "valkrets": "Västra Götalands läns södra",
      "parti": "Sverigedemokraterna",
      "partiförkortning": "SD",
      "ordning": "39",
      "kandidatnummer": "31078"
    },
    {
      "valtyp": "RF",
      "område": "Västra Götaland",
      "valkrets": "Västra Götalands läns östra",
      "parti": "Sverigedemokraterna",
      "partiförkortning": "SD",
      "ordning": "39",
      "kandidatnummer": "31078"
    }
  ]
}