{
  "namn": "Daniel Bernhardt",
  "kandidaturer": [
    {
      "valtyp": "RD",
      "område": "Riket",
      "valkrets": "Hallands län",
      "parti": "Kristdemokraterna",
      "partiförkortning": "KD",
      "ordning": "4",
      "kandidatnummer": "29918"
    },
    {
      "valtyp": "RF",
      "område": "Halland",
      "valkrets": "Halland",
      "parti": "Kristdemokraterna",
      "partiförkortning": "KD",
      "ordning": "22",
      "kandidatnummer": "29918"
    },
    {
      "valtyp": "KF",
      "område": "Falkenberg",
      "valkrets": "Falkenberg",
      "parti": "Kristdemokraterna",
      "partiförkortning": "KD",
      "ordning": "14",
      "kandidatnummer": "29918"
    }
  ]
}