{
  "namn": "Daniel Viberg",
  "kandidaturer": [
    {
      "valtyp": "KF",
      "område": "Jönköping",
      "valkrets": "Jönköping",
      "parti": "Vänsterpartiet",
      "partiförkortning": "V",
      "ordning": "39",
      "kandidatnummer": "46266"
    },
    {
      "valtyp": "KF",
      "område": "Östersund",
      "valkrets": "Östersund",
      "parti": "Arbetarepartiet-Socialdemokraterna",
      "partiförkortning": "S",
      "ordning": "55",
      "kandidatnummer": "12038"
    }
  ]
}