{
  "namn": "Elli-Mari Lundgren",
  "kandidaturer": [
    {
      "valtyp": "RD",
      "område": "Riket",
      "valkrets": "Västerbottens län",
      "parti": "Moderaterna",
      "partiförkortning": "M",
      "ordning": "18",
      "kandidatnummer": "3349"
    },
    {
      "valtyp": "RF",
      "område": "Västerbotten",
      "valkrets": "Västerbottens läns västra",
      "parti": "Moderaterna",
      "partiförkortning": "M",
      "ordning": "26",
      "kandidatnummer": "3349"
    },
    {
      "valtyp": "RF",
      "område": "Västerbotten",
      "valkrets": "Västerbottens läns norra",
      "parti": "Moderaterna",
      "partiförkortning": "M",
      "ordning": "26",
      "kandidatnummer": "3349"
    },
    {
      "valtyp": "RF",
      "område": "Västerbotten",
      "valkrets": "Västerbottens läns södra",
      "parti": "Moderaterna",
      "partiförkortning": "M",
      "ordning": "26",
      "kandidatnummer": "3349"
    },
    {
      "valtyp": "KF",
      "område": "Umeå",
      "valkrets": "Umeå centrala",
      "parti": "Moderaterna",
      "partiförkortning": "M",
      "ordning": "20",
      "kandidatnummer": "3349"
    },
    {
      "valtyp": "KF",
      "område": "Umeå",
      "valkrets": "Umeå omland",
      "parti": "Moderaterna",
      "partiförkortning": "M",
      "ordning": "20",
      "kandidatnummer": "3349"
    }
  ]
}