{
  "namn": "Emilia Brus",
  "kandidaturer": [
    {
      "valtyp": "RF",
      "område": "Dalarna",
      "valkrets": "Region Dalarna",
      "parti": "Arbetarepartiet-Socialdemokraterna",
      "partiförkortning": "S",
      "ordning": "11",
      "kandidatnummer": "6170"
    },
    {
      "valtyp": "KF",
      "område": "Falun",
      "valkrets": "Falun",
      "parti": "Arbetarepartiet-Socialdemokraterna",
      "partiförkortning": "S",
      "ordning": "11",
      "kandidatnummer": "6170"
    }
  ]
}