{
  "namn": "Hasse Hajar",
  "kandidaturer": [
    {
      "valtyp": "KF",
      "område": "Malmö",
      "valkrets": "Malmö Östra",
      "parti": "Arbetarepartiet-Socialdemokraterna",
      "partiförkortning": "S",
      "ordning": "32",
      "kandidatnummer": "47189"
    },
    {
      "valtyp": "KF",
      "område": "Malmö",
      "valkrets": "Malmö Västra",
      "parti": "Arbetarepartiet-Socialdemokraterna",
      "partiförkortning": "S",
      "ordning": "32",
      "kandidatnummer": "47189"
    }
  ]
}