{
  "namn": "Helena Axelsson Fisk",
  "kandidaturer": [
    {
      "valtyp": "RF",
      "område": "Dalarna",
      "valkrets": "Region Dalarna",
      "parti": "Arbetarepartiet-Socialdemokraterna",
      "partiförkortning": "S",
      "ordning": "32",
      "kandidatnummer": "4834"
    },
    {
      "valtyp": "KF",
      "område": "Borlänge",
      "valkrets": "Borlänge",
      "parti": "Arbetarepartiet-Socialdemokraterna",
      "partiförkortning": "S",
      "ordning": "24",
      "kandidatnummer": "4834"
    }
  ]
}