{
  "namn": "Jamie Svensson",
  "kandidaturer": [
    {
      "valtyp": "RD",
      "område": "Riket",
      "valkrets": "Hallands län",
      "parti": "Vänsterpartiet",
      "partiförkortning": "V",
      "ordning": "7",
      "kandidatnummer": "16309"
    },
    {
      "valtyp": "RF",
      "område": "Halland",
      "valkrets": "Halland",
      "parti": "Vänsterpartiet",
      "partiförkortning": "V",
      "ordning": "5",
      "kandidatnummer": "16309"
    },
    {
      "valtyp": "KF",
      "område": "Falkenberg",
      "valkrets": "Falkenberg",
      "parti": "Vänsterpartiet",
      "partiförkortning": "V",
      "ordning": "6",
      "kandidatnummer": "16309"
    }
  ]
}