{
  "namn": "Johanna Magnusson Sjögren",
  "kandidaturer": [
    {
      "valtyp": "RD",
      "område": "Riket",
      "valkrets": "Skåne läns södra",
      "parti": "Centerpartiet",
      "partiförkortning": "C",
      "ordning": "27",
      "kandidatnummer": "31535"
    },
    {
      "valtyp": "RF",
      "område": "Skåne",
      "valkrets": "Nordvästkretsen",
      "parti": "Centerpartiet",
      "partiförkortning": "C",
      "ordning": "17",
      "kandidatnummer": "31535"
    },
    {
      "valtyp": "RF",
      "område": "Skåne",
      "valkrets": "Nordostkretsen",
      "parti": "Centerpartiet",
      "partiförkortning": "C",
      "ordning": "17",
      "kandidatnummer": "31535"
    },
    {
      "valtyp": "RF",
      "område": "Skåne",
      "valkrets": "Mellankretsen",
      "parti": "Centerpartiet",
      "partiförkortning": "C",
      "ordning": "17",
      "kandidatnummer": "31535"
    },
    {
      "valtyp": "RF",
      "område": "Skåne",
      "valkrets": "Sydvästkretsen I",
      "parti": "Centerpartiet",
      "partiförkortning": "C",
      "ordning": "17",
      "kandidatnummer": "31535"
    },
    {
      "valtyp": "RF",
      "område": "Skåne",
      "valkrets": "Sydvästkretsen II",
      "parti": "Centerpartiet",
      "partiförkortning": "C",
      "ordning": "17",
      "kandidatnummer": "31535"
    },
    {
      "valtyp": "RF",
      "område": "Skåne",
      "valkrets": "Sydostkretsen",
      "parti": "Centerpartiet",
      "partiförkortning": "C",
      "ordning": "17",
      "kandidatnummer": "31535"
    },
    {
      "valtyp": "KF",
      "område": "Trelleborg",
      "valkrets": "Trelleborgs  Första, Västra",
      "parti": "Centerpartiet",
      "partiförkortning": "C",
      "ordning": "12",
      "kandidatnummer": "31535"
    },
    {
      "valtyp": "KF",
      "område": "Trelleborg",
      "valkrets": "Trelleborgs Andra, Östra",
      "parti": "Centerpartiet",
      "partiförkortning": "C",
      "ordning": "12",
      "kandidatnummer": "31535"
    }
  ]
}