{
  "namn": "Johanna Modig",
  "kandidaturer": [
    {
      "valtyp": "RF",
      "område": "Norrbotten",
      "valkrets": "Norrbottens läns valkrets",
      "parti": "Sverigedemokraterna",
      "partiförkortning": "SD",
      "ordning": "21",
      "kandidatnummer": "45768"
    },
    {
      "valtyp": "KF",
      "område": "Gällivare",
      "valkrets": "Gällivare",
      "parti": "Sverigedemokraterna",
      "partiförkortning": "SD",
      "ordning": "2",
      "kandidatnummer": "45768"
    }
  ]
}