{
  "namn": "Johannes Fransson",
  "kandidaturer": [
    {
      "valtyp": "RD",
      "område": "Riket",
      "valkrets": "Värmlands län",
      "parti": "Arbetarepartiet-Socialdemokraterna",
      "partiförkortning": "S",
      "ordning": "9",
      "kandidatnummer": "29779"
    },
    {
      "valtyp": "KF",
      "område": "Kristinehamn",
      "valkrets": "Kristinehamn",
      "parti": "Arbetarepartiet-Socialdemokraterna",
      "partiförkortning": "S",
      "ordning": "28",
      "kandidatnummer": "29779"
    }
  ]
}