{
  "namn": "Johan Enfeldt",
  "kandidaturer": [
    {
      "valtyp": "RD",
      "område": "Riket",
      "valkrets": "Uppsala län",
      "parti": "Arbetarepartiet-Socialdemokraterna",
      "partiförkortning": "S",
      "ordning": "31",
      "kandidatnummer": "4970"
    },
    {
      "valtyp": "RF",
      "område": "Uppsala",
      "valkrets": "Uppsala läns södra",
      "parti": "Arbetarepartiet-Socialdemokraterna",
      "partiförkortning": "S",
      "ordning": "14",
      "kandidatnummer": "4970"
    },
    {
      "valtyp": "RF",
      "område": "Uppsala",
      "valkrets": "Uppsala läns mellersta",
      "parti": "Arbetarepartiet-Socialdemokraterna",
      "partiförkortning": "S",
      "ordning": "14",
      "kandidatnummer": "4970"
    },
    {
      "valtyp": "RF",
      "område": "Uppsala",
      "valkrets": "Uppsala läns norra",
      "parti": "Arbetarepartiet-Socialdemokraterna",
      "partiförkortning": "S",
      "ordning": "14",
      "kandidatnummer": "4970"
    },
    {
      "valtyp": "KF",
      "område": "Enköping",
      "valkrets": "Enköping",
      "parti": "Arbetarepartiet-Socialdemokraterna",
      "partiförkortning": "S",
      "ordning": "3",
      "kandidatnummer": "4970"
    }
  ]
}