{
  "namn": "Jonatan Kjellberg",
  "kandidaturer": [
    {
      "valtyp": "RF",
      "område": "Västmanland",
      "valkrets": "Östra valkretsen",
      "parti": "Moderaterna",
      "partiförkortning": "M",
      "ordning": "10",
      "kandidatnummer": "9697"
    },
    {
      "valtyp": "RF",
      "område": "Västmanland",
      "valkrets": "Västra valkretsen",
      "parti": "Moderaterna",
      "partiförkortning": "M",
      "ordning": "10",
      "kandidatnummer": "9697"
    },
    {
      "valtyp": "KF",
      "område": "Surahammar",
      "valkrets": "Surahammar",
      "parti": "Moderaterna",
      "partiförkortning": "M",
      "ordning": "3",
      "kandidatnummer": "9697"
    }
  ]
}