{
  "namn": "Lars-Göran Karlsson",
  "kandidaturer": [
    {
      "valtyp": "RD",
      "område": "Riket",
      "valkrets": "Södermanlands län",
      "parti": "Sverigedemokraterna",
      "partiförkortning": "SD",
      "ordning": "72",
      "kandidatnummer": "830"
    },
    {
      "valtyp": "RF",
      "område": "Södermanland",
      "valkrets": "Region Södermanland",
      "parti": "Sverigedemokraterna",
      "partiförkortning": "SD",
      "ordning": "7",
      "kandidatnummer": "830"
    },
    {
      "valtyp": "KF",
      "område": "Vingåker",
      "valkrets": "Vingåker",
      "parti": "Sverigedemokraterna",
      "partiförkortning": "SD",
      "ordning": "1",
      "kandidatnummer": "830"
    },
    {
      "valtyp": "KF",
      "område": "Eskilstuna",
      "valkrets": "Eskilstuna",
      "parti": "Arbetarepartiet-Socialdemokraterna",
      "partiförkortning": "S",
      "ordning": "10",
      "kandidatnummer": "33592"
    },
    {
      "valtyp": "KF",
      "område": "Hammarö",
      "valkrets": "Hammarö",
      "parti": "Sverigedemokraterna",
      "partiförkortning": "SD",
      "ordning": "8",
      "kandidatnummer": "33771"
    }
  ]
}