{
  "namn": "Lars-Erik Persson",
  "kandidaturer": [
    {
      "valtyp": "KF",
      "område": "Karlskrona",
      "valkrets": "Karlskrona Ö",
      "parti": "Sverigedemokraterna",
      "partiförkortning": "SD",
      "ordning": "25",
      "kandidatnummer": "43904"
    },
    {
      "valtyp": "KF",
      "område": "Karlskrona",
      "valkrets": "Karlskrona V",
      "parti": "Sverigedemokraterna",
      "partiförkortning": "SD",
      "ordning": "25",
      "kandidatnummer": "43904"
    },
    {
      "valtyp": "KF",
      "område": "Karlskrona",
      "valkrets": "Karlskrona C",
      "parti": "Sverigedemokraterna",
      "partiförkortning": "SD",
      "ordning": "25",
      "kandidatnummer": "43904"
    }
  ]
}