{
  "namn": "Lennart Jonsson",
  "kandidaturer": [
    {
      "valtyp": "RD",
      "område": "Riket",
      "valkrets": "Västra Götalands läns västra",
      "parti": "Sverigedemokraterna",
      "partiförkortning": "SD",
      "ordning": "69",
      "kandidatnummer": "17040"
    },
    {
      "valtyp": "RF",
      "område": "Västra Götaland",
      "valkrets": "Göteborgs kommun",
      "parti": "Sverigedemokraterna",
      "partiförkortning": "SD",
      "ordning": "13",
      "kandidatnummer": "17040"
    },
    {
      "valtyp": "RF",
      "område": "Västra Götaland",
      "valkrets": "Västra Götalands läns västra",
      "parti": "Sverigedemokraterna",
      "partiförkortning": "SD",
      "ordning": "13",
      "kandidatnummer": "17040"
    },
    {
      "valtyp": "RF",
      "område": "Västra Götaland",
      "valkrets": "Västra Götalands läns norra",
      "parti": "Sverigedemokraterna",
      "partiförkortning": "SD",
      "ordning": "13",
      "kandidatnummer": "17040"
    },
    {
      "valtyp": "RF",
      "område": "Västra Götaland",
      "valkrets": "Västra Götalands läns södra",
      "parti": "Sverigedemokraterna",
      "partiförkortning": "SD",
      "ordning": "13",
      "kandidatnummer": "17040"
    },
    {
      "valtyp": "RF",
      "område": "Västra Götaland",
      "valkrets": "Västra Götalands läns östra",
      "parti": "Sverigedemokraterna",
      "partiförkortning": "SD",
      "ordning": "13",
      "kandidatnummer": "17040"
    },
    {
      "valtyp": "KF",
      "område": "Mölndal",
      "valkrets": "Mölndal",
      "parti": "Sverigedemokraterna",
      "partiförkortning": "SD",
      "ordning": "1",
      "kandidatnummer": "17040"
    },
    {
      "valtyp": "KF",
      "område": "Kungälv",
      "valkrets": "Kungälv",
      "parti": "Moderaterna",
      "partiförkortning": "M",
      "ordning": "32",
      "kandidatnummer": "19142"
    }
  ]
}