{
  "namn": "Loke Carstinge",
  "kandidaturer": [
    {
      "valtyp": "RF",
      "område": "Västmanland",
      "valkrets": "Östra valkretsen",
      "parti": "Sverigedemokraterna",
      "partiförkortning": "SD",
      "ordning": "28",
      "kandidatnummer": "47950"
    },
    {
      "valtyp": "RF",
      "område": "Västmanland",
      "valkrets": "Västra valkretsen",
      "parti": "Sverigedemokraterna",
      "partiförkortning": "SD",
      "ordning": "28",
      "kandidatnummer": "47950"
    }
  ]
}