{
  "namn": "Lucas Lindh",
  "kandidaturer": [
    {
      "valtyp": "RD",
      "område": "Riket",
      "valkrets": "Västerbottens län",
      "parti": "Moderaterna",
      "partiförkortning": "M",
      "ordning": "9",
      "kandidatnummer": "3340"
    },
    {
      "valtyp": "RF",
      "område": "Västerbotten",
      "valkrets": "Västerbottens läns västra",
      "parti": "Moderaterna",
      "partiförkortning": "M",
      "ordning": "64",
      "kandidatnummer": "3340"
    },
    {
      "valtyp": "RF",
      "område": "Västerbotten",
      "valkrets": "Västerbottens läns norra",
      "parti": "Moderaterna",
      "partiförkortning": "M",
      "ordning": "64",
      "kandidatnummer": "3340"
    },
    {
      "valtyp": "RF",
      "område": "Västerbotten",
      "valkrets": "Västerbottens läns södra",
      "parti": "Moderaterna",
      "partiförkortning": "M",
      "ordning": "64",
      "kandidatnummer": "3340"
    },
    {
      "valtyp": "KF",
      "område": "Skellefteå",
      "valkrets": "Skellefteå",
      "parti": "Moderaterna",
      "partiförkortning": "M",
      "ordning": "3",
      "kandidatnummer": "3340"
    }
  ]
}