{
  "namn": "Malin Westerlund",
  "kandidaturer": [
    {
      "valtyp": "RD",
      "område": "Riket",
      "valkrets": "Västerbottens län",
      "parti": "Miljöpartiet de gröna",
      "partiförkortning": "MP",
      "ordning": "12",
      "kandidatnummer": "30779"
    },
    {
      "valtyp": "RF",
      "område": "Västerbotten",
      "valkrets": "Västerbottens läns västra",
      "parti": "Miljöpartiet de gröna",
      "partiförkortning": "MP",
      "ordning": "5",
      "kandidatnummer": "30779"
    },
    {
      "valtyp": "RF",
      "område": "Västerbotten",
      "valkrets": "Västerbottens läns västra",
      "parti": "Miljöpartiet de gröna",
      "partiförkortning": "MP",
      "ordning": "14",
      "kandidatnummer": "30779"
    },
    {
      "valtyp": "RF",
      "område": "Västerbotten",
      "valkrets": "Västerbottens läns västra",
      "parti": "Miljöpartiet de gröna",
      "partiförkortning": "MP",
      "ordning": "17",
      "kandidatnummer": "30779"
    },
    {
      "valtyp": "RF",
      "område": "Västerbotten",
      "valkrets": "Västerbottens läns norra",
      "parti": "Miljöpartiet de gröna",
      "partiförkortning": "MP",
      "ordning": "5",
      "kandidatnummer": "30779"
    },
    {
      "valtyp": "RF",
      "område": "Västerbotten",
      "valkrets": "Västerbottens läns norra",
      "parti": "Miljöpartiet de gröna",
      "partiförkortning": "MP",
      "ordning": "14",
      "kandidatnummer": "30779"
    },
    {
      "valtyp": "RF",
      "område": "Västerbotten",
      "valkrets": "Västerbottens läns norra",
      "parti": "Miljöpartiet de gröna",
      "partiförkortning": "MP",
      "ordning": "17",
      "kandidatnummer": "30779"
    },
    {
      "valtyp": "RF",
      "område": "Västerbotten",
      "valkrets": "Västerbottens läns södra",
      "parti": "Miljöpartiet de gröna",
      "partiförkortning": "MP",
      "ordning": "5",
      "kandidatnummer": "30779"
    },
    {
      "valtyp": "RF",
      "område": "Västerbotten",
      "valkrets": "Västerbottens läns södra",
      "parti": "Miljöpartiet de gröna",
      "partiförkortning": "MP",
      "ordning": "14",
      "kandidatnummer": "30779"
    },
    {
      "valtyp": "RF",
      "område": "Västerbotten",
      "valkrets": "Västerbottens läns södra",
      "parti": "Miljöpartiet de gröna",
      "partiförkortning": "MP",
      "ordning": "17",
      "kandidatnummer": "30779"
    },
    {
      "valtyp": "KF",
      "område": "Skellefteå",
      "valkrets": "Skellefteå",
      "parti": "Miljöpartiet de gröna",
      "partiförkortning": "MP",
      "ordning": "2",
      "kandidatnummer": "30779"
    }
  ]
}