{
  "namn": "Maria Lindquist",
  "kandidaturer": [
    {
      "valtyp": "RF",
      "område": "Värmland",
      "valkrets": "Region Värmland",
      "parti": "Centerpartiet",
      "partiförkortning": "C",
      "ordning": "48",
      "kandidatnummer": "8465"
    },
    {
      "valtyp": "KF",
      "område": "Gnosjö",
      "valkrets": "Gnosjö",
      "parti": "Arbetarepartiet-Socialdemokraterna",
      "partiförkortning": "S",
      "ordning": "13",
      "kandidatnummer": "24882"
    },
    {
      "valtyp": "KF",
      "område": "Forshaga",
      "valkrets": "Forshaga",
      "parti": "Centerpartiet",
      "partiförkortning": "C",
      "ordning": "13",
      "kandidatnummer": "8465"
    }
  ]
}