{
  "namn": "Maria Lidzell",
  "kandidaturer": [
    {
      "valtyp": "RF",
      "område": "Stockholm",
      "valkrets": "1 Södermalm-Enskede",
      "parti": "Liberalerna (tidigare Folkpartiet)",
      "partiförkortning": "L",
      "ordning": "13",
      "kandidatnummer": "6701"
    },
    {
      "valtyp": "RF",
      "område": "Stockholm",
      "valkrets": "2 Bromma-Kungsholmen",
      "parti": "Liberalerna (tidigare Folkpartiet)",
      "partiförkortning": "L",
      "ordning": "13",
      "kandidatnummer": "6701"
    },
    {
      "valtyp": "RF",
      "område": "Stockholm",
      "valkrets": "3 Norrmalm-Östermalm-Gamla Stan",
      "parti": "Liberalerna (tidigare Folkpartiet)",
      "partiförkortning": "L",
      "ordning": "13",
      "kandidatnummer": "6701"
    },
    {
      "valtyp": "RF",
      "område": "Stockholm",
      "valkrets": "4 Östra Söderort",
      "parti": "Liberalerna (tidigare Folkpartiet)",
      "partiförkortning": "L",
      "ordning": "13",
      "kandidatnummer": "6701"
    },
    {
      "valtyp": "RF",
      "område": "Stockholm",
      "valkrets": "5 Västra Söderort",
      "parti": "Liberalerna (tidigare Folkpartiet)",
      "partiförkortning": "L",
      "ordning": "13",
      "kandidatnummer": "6701"
    },
    {
      "valtyp": "RF",
      "område": "Stockholm",
      "valkrets": "6 Yttre Västerort",
      "parti": "Liberalerna (tidigare Folkpartiet)",
      "partiförkortning": "L",
      "ordning": "13",
      "kandidatnummer": "6701"
    },
    {
      "valtyp": "RF",
      "område": "Stockholm",
      "valkrets": "Sydväst",
      "parti": "Liberalerna (tidigare Folkpartiet)",
      "partiförkortning": "L",
      "ordning": "13",
      "kandidatnummer": "6701"
    },
    {
      "valtyp": "RF",
      "område": "Stockholm",
      "valkrets": "Sydost",
      "parti": "Liberalerna (tidigare Folkpartiet)",
      "partiförkortning": "L",
      "ordning": "13",
      "kandidatnummer": "6701"
    },
    {
      "valtyp": "RF",
      "område": "Stockholm",
      "valkrets": "Ost",
      "parti": "Liberalerna (tidigare Folkpartiet)",
      "partiförkortning": "L",
      "ordning": "13",
      "kandidatnummer": "6701"
    },
    {
      "valtyp": "RF",
      "område": "Stockholm",
      "valkrets": "Nordost",
      "parti": "Liberalerna (tidigare Folkpartiet)",
      "partiförkortning": "L",
      "ordning": "13",
      "kandidatnummer": "6701"
    },
    {
      "valtyp": "RF",
      "område": "Stockholm",
      "valkrets": "Nord",
      "parti": "Liberalerna (tidigare Folkpartiet)",
      "partiförkortning": "L",
      "ordning": "13",
      "kandidatnummer": "6701"
    },
    {
      "valtyp": "RF",
      "område": "Stockholm",
      "valkrets": "Nordväst",
      "parti": "Liberalerna (tidigare Folkpartiet)",
      "partiförkortning": "L",
      "ordning": "13",
      "kandidatnummer": "6701"
    },
    {
      "valtyp": "KF",
      "område": "Nacka",
      "valkrets": "Nacka Västra",
      "parti": "Liberalerna (tidigare Folkpartiet)",
      "partiförkortning": "L",
      "ordning": "6",
      "kandidatnummer": "6701"
    },
    {
      "valtyp": "KF",
      "område": "Nacka",
      "valkrets": "Nacka  Östra",
      "parti": "Liberalerna (tidigare Folkpartiet)",
      "partiförkortning": "L",
      "ordning": "6",
      "kandidatnummer": "6701"
    }
  ]
}