{
  "namn": "Mats Annerfeldt",
  "kandidaturer": [
    {
      "valtyp": "RD",
      "område": "Riket",
      "valkrets": "Östergötlands län",
      "parti": "Arbetarepartiet-Socialdemokraterna",
      "partiförkortning": "S",
      "ordning": "28",
      "kandidatnummer": "29996"
    },
    {
      "valtyp": "KF",
      "område": "Finspång",
      "valkrets": "Finspång",
      "parti": "Arbetarepartiet-Socialdemokraterna",
      "partiförkortning": "S",
      "ordning": "1",
      "kandidatnummer": "29996"
    }
  ]
}