{
  "namn": "Mikael Pihlgren",
  "kandidaturer": [
    {
      "valtyp": "RF",
      "område": "Örebro",
      "valkrets": "Örebro läns Södra",
      "parti": "Sverigedemokraterna",
      "partiförkortning": "SD",
      "ordning": "20",
      "kandidatnummer": "41170"
    },
    {
      "valtyp": "RF",
      "område": "Örebro",
      "valkrets": "Örebro läns Södra",
      "parti": "Sverigedemokraterna",
      "partiförkortning": "SD",
      "ordning": "18",
      "kandidatnummer": "41170"
    },
    {
      "valtyp": "RF",
      "område": "Örebro",
      "valkrets": "Örebro läns Södra",
      "parti": "Sverigedemokraterna",
      "partiförkortning": "SD",
      "ordning": "4",
      "kandidatnummer": "41170"
    },
    {
      "valtyp": "RF",
      "område": "Örebro",
      "valkrets": "Örebro läns Södra",
      "parti": "Sverigedemokraterna",
      "partiförkortning": "SD",
      "ordning": "31",
      "kandidatnummer": "41170"
    },
    {
      "valtyp": "RF",
      "område": "Örebro",
      "valkrets": "Örebro läns Västra",
      "parti": "Sverigedemokraterna",
      "partiförkortning": "SD",
      "ordning": "20",
      "kandidatnummer": "41170"
    },
    {
      "valtyp": "RF",
      "område": "Örebro",
      "valkrets": "Örebro läns Västra",
      "parti": "Sverigedemokraterna",
      "partiförkortning": "SD",
      "ordning": "18",
      "kandidatnummer": "41170"
    },
    {
      "valtyp": "RF",
      "område": "Örebro",
      "valkrets": "Örebro läns Västra",
      "parti": "Sverigedemokraterna",
      "partiförkortning": "SD",
      "ordning": "4",
      "kandidatnummer": "41170"
    },
    {
      "valtyp": "RF",
      "område": "Örebro",
      "valkrets": "Örebro läns Västra",
      "parti": "Sverigedemokraterna",
      "partiförkortning": "SD",
      "ordning": "31",
      "kandidatnummer": "41170"
    },
    {
      "valtyp": "RF",
      "område": "Örebro",
      "valkrets": "Örebro-Lekeberg",
      "parti": "Sverigedemokraterna",
      "partiförkortning": "SD",
      "ordning": "20",
      "kandidatnummer": "41170"
    },
    {
      "valtyp": "RF",
      "område": "Örebro",
      "valkrets": "Örebro-Lekeberg",
      "parti": "Sverigedemokraterna",
      "partiförkortning": "SD",
      "ordning": "18",
      "kandidatnummer": "41170"
    },
    {
      "valtyp": "RF",
      "område": "Örebro",
      "valkrets": "Örebro-Lekeberg",
      "parti": "Sverigedemokraterna",
      "partiförkortning": "SD",
      "ordning": "4",
      "kandidatnummer": "41170"
    },
    {
      "valtyp": "RF",
      "område": "Örebro",
      "valkrets": "Örebro-Lekeberg",
      "parti": "Sverigedemokraterna",
      "partiförkortning": "SD",
      "ordning": "31",
      "kandidatnummer": "41170"
    },
    {
      "valtyp": "RF",
      "område": "Örebro",
      "valkrets": "Örebro läns Norra",
      "parti": "Sverigedemokraterna",
      "partiförkortning": "SD",
      "ordning": "20",
      "kandidatnummer": "41170"
    },
    {
      "valtyp": "RF",
      "område": "Örebro",
      "valkrets": "Örebro läns Norra",
      "parti": "Sverigedemokraterna",
      "partiförkortning": "SD",
      "ordning": "18",
      "kandidatnummer": "41170"
    },
    {
      "valtyp": "RF",
      "område": "Örebro",
      "valkrets": "Örebro läns Norra",
      "parti": "Sverigedemokraterna",
      "partiförkortning": "SD",
      "ordning": "4",
      "kandidatnummer": "41170"
    },
    {
      "valtyp": "RF",
      "område": "Örebro",
      "valkrets": "Örebro läns Norra",
      "parti": "Sverigedemokraterna",
      "partiförkortning": "SD",
      "ordning": "31",
      "kandidatnummer": "41170"
    },
    {
      "valtyp": "KF",
      "område": "Karlskoga",
      "valkrets": "Karlskoga",
      "parti": "Sverigedemokraterna",
      "partiförkortning": "SD",
      "ordning": "3",
      "kandidatnummer": "41170"
    }
  ]
}