{
  "namn": "Mikael Bengtsson",
  "kandidaturer": [
    {
      "valtyp": "RF",
      "område": "Kronoberg",
      "valkrets": "Kronoberg",
      "parti": "Sverigedemokraterna",
      "partiförkortning": "SD",
      "ordning": "23",
      "kandidatnummer": "37434"
    },
    {
      "valtyp": "KF",
      "område": "Ljungby",
      "valkrets": "Ljungby",
      "parti": "Sverigedemokraterna",
      "partiförkortning": "SD",
      "ordning": "9",
      "kandidatnummer": "37434"
    },
    {
      "valtyp": "KF",
      "område": "Kungälv",
      "valkrets": "Kungälv",
      "parti": "Arbetarepartiet-Socialdemokraterna",
      "partiförkortning": "S",
      "ordning": "29",
      "kandidatnummer": "47646"
    },
    {
      "valtyp": "KF",
      "område": "Borås",
      "valkrets": "Borås Östra 1",
      "parti": "Centerpartiet",
      "partiförkortning": "C",
      "ordning": "19",
      "kandidatnummer": "12902"
    },
    {
      "valtyp": "KF",
      "område": "Borås",
      "valkrets": "Borås Södra 2",
      "parti": "Centerpartiet",
      "partiförkortning": "C",
      "ordning": "19",
      "kandidatnummer": "12902"
    },
    {
      "valtyp": "KF",
      "område": "Borås",
      "valkrets": "Borås Västra 3",
      "parti": "Centerpartiet",
      "partiförkortning": "C",
      "ordning": "19",
      "kandidatnummer": "12902"
    }
  ]
}