{
  "namn": "Nils Lindberg",
  "kandidaturer": [
    {
      "valtyp": "RF",
      "område": "Jämtland",
      "valkrets": "Jämtland/Härjedalen",
      "parti": "Arbetarepartiet-Socialdemokraterna",
      "partiförkortning": "S",
      "ordning": "49",
      "kandidatnummer": "5446"
    },
    {
      "valtyp": "KF",
      "område": "Östersund",
      "valkrets": "Östersund",
      "parti": "Arbetarepartiet-Socialdemokraterna",
      "partiförkortning": "S",
      "ordning": "11",
      "kandidatnummer": "5446"
    }
  ]
}