{
  "namn": "Pernilla Eklund",
  "kandidaturer": [
    {
      "valtyp": "RD",
      "område": "Riket",
      "valkrets": "Dalarnas län",
      "parti": "Centerpartiet",
      "partiförkortning": "C",
      "ordning": "21",
      "kandidatnummer": "2173"
    },
    {
      "valtyp": "RF",
      "område": "Dalarna",
      "valkrets": "Region Dalarna",
      "parti": "Centerpartiet",
      "partiförkortning": "C",
      "ordning": "10",
      "kandidatnummer": "2173"
    },
    {
      "valtyp": "KF",
      "område": "Avesta",
      "valkrets": "Avesta",
      "parti": "Centerpartiet",
      "partiförkortning": "C",
      "ordning": "1",
      "kandidatnummer": "2173"
    }
  ]
}