{
  "namn": "Peter Jeppsson",
  "kandidaturer": [
    {
      "valtyp": "KF",
      "område": "Sölvesborg",
      "valkrets": "Sölvesborg",
      "parti": "Arbetarepartiet-Socialdemokraterna",
      "partiförkortning": "S",
      "ordning": "48",
      "kandidatnummer": "39458"
    },
    {
      "valtyp": "KF",
      "område": "Ljusnarsberg",
      "valkrets": "Ljusnarsberg",
      "parti": "Sverigedemokraterna",
      "partiförkortning": "SD",
      "ordning": "7",
      "kandidatnummer": "54176"
    }
  ]
}