{
  "namn": "Peter Janson",
  "kandidaturer": [
    {
      "valtyp": "RD",
      "område": "Riket",
      "valkrets": "Skåne läns västra",
      "parti": "Centerpartiet",
      "partiförkortning": "C",
      "ordning": "8",
      "kandidatnummer": "31740"
    },
    {
      "valtyp": "RF",
      "område": "Skåne",
      "valkrets": "Nordvästkretsen",
      "parti": "Centerpartiet",
      "partiförkortning": "C",
      "ordning": "26",
      "kandidatnummer": "31740"
    },
    {
      "valtyp": "RF",
      "område": "Skåne",
      "valkrets": "Nordostkretsen",
      "parti": "Centerpartiet",
      "partiförkortning": "C",
      "ordning": "26",
      "kandidatnummer": "31740"
    },
    {
      "valtyp": "RF",
      "område": "Skåne",
      "valkrets": "Mellankretsen",
      "parti": "Centerpartiet",
      "partiförkortning": "C",
      "ordning": "26",
      "kandidatnummer": "31740"
    },
    {
      "valtyp": "RF",
      "område": "Skåne",
      "valkrets": "Sydvästkretsen I",
      "parti": "Centerpartiet",
      "partiförkortning": "C",
      "ordning": "26",
      "kandidatnummer": "31740"
    },
    {
      "valtyp": "RF",
      "område": "Skåne",
      "valkrets": "Sydvästkretsen II",
      "parti": "Centerpartiet",
      "partiförkortning": "C",
      "ordning": "26",
      "kandidatnummer": "31740"
    },
    {
      "valtyp": "RF",
      "område": "Skåne",
      "valkrets": "Sydostkretsen",
      "parti": "Centerpartiet",
      "partiförkortning": "C",
      "ordning": "26",
      "kandidatnummer": "31740"
    },
    {
      "valtyp": "KF",
      "område": "Helsingborg",
      "valkrets": "Helsingborg",
      "parti": "Centerpartiet",
      "partiförkortning": "C",
      "ordning": "9",
      "kandidatnummer": "31740"
    },
    {
      "valtyp": "KF",
      "område": "Falkenberg",
      "valkrets": "Falkenberg",
      "parti": "Arbetarepartiet-Socialdemokraterna",
      "partiförkortning": "S",
      "ordning": "49",
      "kandidatnummer": "35030"
    }
  ]
}