{
  "namn": "Robert Gjersvold",
  "kandidaturer": [
    {
      "valtyp": "RD",
      "område": "Riket",
      "valkrets": "Jämtlands län",
      "parti": "Sverigedemokraterna",
      "partiförkortning": "SD",
      "ordning": "67",
      "kandidatnummer": "2904"
    },
    {
      "valtyp": "RF",
      "område": "Jämtland",
      "valkrets": "Jämtland/Härjedalen",
      "parti": "Sverigedemokraterna",
      "partiförkortning": "SD",
      "ordning": "4",
      "kandidatnummer": "2904"
    },
    {
      "valtyp": "KF",
      "område": "Strömsund",
      "valkrets": "Strömsund",
      "parti": "Sverigedemokraterna",
      "partiförkortning": "SD",
      "ordning": "1",
      "kandidatnummer": "2904"
    }
  ]
}