{
  "namn": "Susanne Agorander",
  "kandidaturer": [
    {
      "valtyp": "RD",
      "område": "Riket",
      "valkrets": "Värmlands län",
      "parti": "Miljöpartiet de gröna",
      "partiförkortning": "MP",
      "ordning": "19",
      "kandidatnummer": "32348"
    },
    {
      "valtyp": "RF",
      "område": "Värmland",
      "valkrets": "Region Värmland",
      "parti": "Miljöpartiet de gröna",
      "partiförkortning": "MP",
      "ordning": "30",
      "kandidatnummer": "32348"
    }
  ]
}