{
  "namn": "Thomas Carlsson",
  "kandidaturer": [
    {
      "valtyp": "KF",
      "område": "Grästorp",
      "valkrets": "Grästorp",
      "parti": "FRAM FÖR KOMMUNEN",
      "partiförkortning": "FFK",
      "ordning": "4",
      "kandidatnummer": "44568"
    },
    {
      "valtyp": "KF",
      "område": "Svenljunga",
      "valkrets": "Svenljunga",
      "parti": "Landsbygdspartiet Oberoende",
      "partiförkortning": "LPo",
      "ordning": "3",
      "kandidatnummer": "53914"
    },
    {
      "valtyp": "KF",
      "område": "Tibro",
      "valkrets": "Tibro",
      "parti": "Arbetarepartiet-Socialdemokraterna",
      "partiförkortning": "S",
      "ordning": "13",
      "kandidatnummer": "49024"
    },
    {
      "valtyp": "KF",
      "område": "Ljusnarsberg",
      "valkrets": "Ljusnarsberg",
      "parti": "Sverigedemokraterna",
      "partiförkortning": "SD",
      "ordning": "4",
      "kandidatnummer": "54173"
    }
  ]
}