{
  "namn": "Ulf Johansson",
  "kandidaturer": [
    {
      "valtyp": "RF",
      "område": "Stockholm",
      "valkrets": "1 Södermalm-Enskede",
      "parti": "Sverigedemokraterna",
      "partiförkortning": "SD",
      "ordning": "52",
      "kandidatnummer": "43345"
    },
    {
      "valtyp": "RF",
      "område": "Stockholm",
      "valkrets": "2 Bromma-Kungsholmen",
      "parti": "Sverigedemokraterna",
      "partiförkortning": "SD",
      "ordning": "52",
      "kandidatnummer": "43345"
    },
    {
      "valtyp": "RF",
      "område": "Stockholm",
      "valkrets": "3 Norrmalm-Östermalm-Gamla Stan",
      "parti": "Sverigedemokraterna",
      "partiförkortning": "SD",
      "ordning": "52",
      "kandidatnummer": "43345"
    },
    {
      "valtyp": "RF",
      "område": "Stockholm",
      "valkrets": "4 Östra Söderort",
      "parti": "Sverigedemokraterna",
      "partiförkortning": "SD",
      "ordning": "52",
      "kandidatnummer": "43345"
    },
    {
      "valtyp": "RF",
      "område": "Stockholm",
      "valkrets": "5 Västra Söderort",
      "parti": "Sverigedemokraterna",
      "partiförkortning": "SD",
      "ordning": "52",
      "kandidatnummer": "43345"
    },
    {
      "valtyp": "RF",
      "område": "Stockholm",
      "valkrets": "6 Yttre Västerort",
      "parti": "Sverigedemokraterna",
      "partiförkortning": "SD",
      "ordning": "52",
      "kandidatnummer": "43345"
    },
    {
      "valtyp": "RF",
      "område": "Stockholm",
      "valkrets": "Sydväst",
      "parti": "Sverigedemokraterna",
      "partiförkortning": "SD",
      "ordning": "52",
      "kandidatnummer": "43345"
    },
    {
      "valtyp": "RF",
      "område": "Stockholm",
      "valkrets": "Sydost",
      "parti": "Sverigedemokraterna",
      "partiförkortning": "SD",
      "ordning": "52",
      "kandidatnummer": "43345"
    },
    {
      "valtyp": "RF",
      "område": "Stockholm",
      "valkrets": "Ost",
      "parti": "Sverigedemokraterna",
      "partiförkortning": "SD",
      "ordning": "52",
      "kandidatnummer": "43345"
    },
    {
      "valtyp": "RF",
      "område": "Stockholm",
      "valkrets": "Nordost",
      "parti": "Sverigedemokraterna",
      "partiförkortning": "SD",
      "ordning": "52",
      "kandidatnummer": "43345"
    },
    {
      "valtyp": "RF",
      "område": "Stockholm",
      "valkrets": "Nord",
      "parti": "Sverigedemokraterna",
      "partiförkortning": "SD",
      "ordning": "52",
      "kandidatnummer": "43345"
    },
    {
      "valtyp": "RF",
      "område": "Stockholm",
      "valkrets": "Nordväst",
      "parti": "Sverigedemokraterna",
      "partiförkortning": "SD",
      "ordning": "52",
      "kandidatnummer": "43345"
    },
    {
      "valtyp": "KF",
      "område": "Järfälla",
      "valkrets": "Järfälla",
      "parti": "Kristdemokraterna",
      "partiförkortning": "KD",
      "ordning": "15",
      "kandidatnummer": "36690"
    },
    {
      "valtyp": "KF",
      "område": "Botkyrka",
      "valkrets": "Botkyrka",
      "parti": "Sverigedemokraterna",
      "partiförkortning": "SD",
      "ordning": "28",
      "kandidatnummer": "43345"
    },
    {
      "valtyp": "KF",
      "område": "Nacka",
      "valkrets": "Nacka Västra",
      "parti": "Kristdemokraterna",
      "partiförkortning": "KD",
      "ordning": "39",
      "kandidatnummer": "28236"
    },
    {
      "valtyp": "KF",
      "område": "Nacka",
      "valkrets": "Nacka  Östra",
      "parti": "Kristdemokraterna",
      "partiförkortning": "KD",
      "ordning": "39",
      "kandidatnummer": "28236"
    },
    {
      "valtyp": "KF",
      "område": "Kinda",
      "valkrets": "Kinda",
      "parti": "Arbetarepartiet-Socialdemokraterna",
      "partiförkortning": "S",
      "ordning": "12",
      "kandidatnummer": "25050"
    },
    {
      "valtyp": "KF",
      "område": "Laholm",
      "valkrets": "Laholm",
      "parti": "Laholmspartiet",
      "partiförkortning": "Lap",
      "ordning": "7",
      "kandidatnummer": "25591"
    },
    {
      "valtyp": "KF",
      "område": "Nordmaling",
      "valkrets": "Nordmaling",
      "parti": "Centerpartiet",
      "partiförkortning": "C",
      "ordning": "24",
      "kandidatnummer": "36279"
    }
  ]
}