{
  "namn": "Ulf Andersson",
  "kandidaturer": [
    {
      "valtyp": "RF",
      "område": "Stockholm",
      "valkrets": "1 Södermalm-Enskede",
      "parti": "Sverigedemokraterna",
      "partiförkortning": "SD",
      "ordning": "44",
      "kandidatnummer": "42544"
    },
    {
      "valtyp": "RF",
      "område": "Stockholm",
      "valkrets": "2 Bromma-Kungsholmen",
      "parti": "Sverigedemokraterna",
      "partiförkortning": "SD",
      "ordning": "44",
      "kandidatnummer": "42544"
    },
    {
      "valtyp": "RF",
      "område": "Stockholm",
      "valkrets": "3 Norrmalm-Östermalm-Gamla Stan",
      "parti": "Sverigedemokraterna",
      "partiförkortning": "SD",
      "ordning": "44",
      "kandidatnummer": "42544"
    },
    {
      "valtyp": "RF",
      "område": "Stockholm",
      "valkrets": "4 Östra Söderort",
      "parti": "Sverigedemokraterna",
      "partiförkortning": "SD",
      "ordning": "44",
      "kandidatnummer": "42544"
    },
    {
      "valtyp": "RF",
      "område": "Stockholm",
      "valkrets": "5 Västra Söderort",
      "parti": "Sverigedemokraterna",
      "partiförkortning": "SD",
      "ordning": "44",
      "kandidatnummer": "42544"
    },
    {
      "valtyp": "RF",
      "område": "Stockholm",
      "valkrets": "6 Yttre Västerort",
      "parti": "Sverigedemokraterna",
      "partiförkortning": "SD",
      "ordning": "44",
      "kandidatnummer": "42544"
    },
    {
      "valtyp": "RF",
      "område": "Stockholm",
      "valkrets": "Sydväst",
      "parti": "Sverigedemokraterna",
      "partiförkortning": "SD",
      "ordning": "44",
      "kandidatnummer": "42544"
    },
    {
      "valtyp": "RF",
      "område": "Stockholm",
      "valkrets": "Sydost",
      "parti": "Sverigedemokraterna",
      "partiförkortning": "SD",
      "ordning": "44",
      "kandidatnummer": "42544"
    },
    {
      "valtyp": "RF",
      "område": "Stockholm",
      "valkrets": "Ost",
      "parti": "Sverigedemokraterna",
      "partiförkortning": "SD",
      "ordning": "44",
      "kandidatnummer": "42544"
    },
    {
      "valtyp": "RF",
      "område": "Stockholm",
      "valkrets": "Nordost",
      "parti": "Sverigedemokraterna",
      "partiförkortning": "SD",
      "ordning": "44",
      "kandidatnummer": "42544"
    },
    {
      "valtyp": "RF",
      "område": "Stockholm",
      "valkrets": "Nord",
      "parti": "Sverigedemokraterna",
      "partiförkortning": "SD",
      "ordning": "44",
      "kandidatnummer": "42544"
    },
    {
      "valtyp": "RF",
      "område": "Stockholm",
      "valkrets": "Nordväst",
      "parti": "Sverigedemokraterna",
      "partiförkortning": "SD",
      "ordning": "44",
      "kandidatnummer": "42544"
    },
    {
      "valtyp": "RF",
      "område": "Västernorrland",
      "valkrets": "Region Västernorrland",
      "parti": "Sverigedemokraterna",
      "partiförkortning": "SD",
      "ordning": "14",
      "kandidatnummer": "31297"
    },
    {
      "valtyp": "KF",
      "område": "Nykvarn",
      "valkrets": "Nykvarn",
      "parti": "Moderaterna",
      "partiförkortning": "M",
      "ordning": "17",
      "kandidatnummer": "17787"
    },
    {
      "valtyp": "KF",
      "område": "Norrtälje",
      "valkrets": "Norrtälje",
      "parti": "Sverigedemokraterna",
      "partiförkortning": "SD",
      "ordning": "22",
      "kandidatnummer": "42544"
    },
    {
      "valtyp": "KF",
      "område": "Tierp",
      "valkrets": "Tierp",
      "parti": "Arbetarepartiet-Socialdemokraterna",
      "partiförkortning": "S",
      "ordning": "30",
      "kandidatnummer": "29189"
    },
    {
      "valtyp": "KF",
      "område": "Östhammar",
      "valkrets": "Östhammar",
      "parti": "Lokalpartiet BoA",
      "partiförkortning": "BoA",
      "ordning": "8",
      "kandidatnummer": "55596"
    },
    {
      "valtyp": "KF",
      "område": "Tranås",
      "valkrets": "Tranås",
      "parti": "Sverigedemokraterna",
      "partiförkortning": "SD",
      "ordning": "7",
      "kandidatnummer": "6393"
    },
    {
      "valtyp": "KF",
      "område": "Tomelilla",
      "valkrets": "Tomelilla",
      "parti": "Sverigedemokraterna",
      "partiförkortning": "SD",
      "ordning": "23",
      "kandidatnummer": "20854"
    },
    {
      "valtyp": "KF",
      "område": "Hylte",
      "valkrets": "Hylte",
      "parti": "Kommunens Väl",
      "partiförkortning": "Komv",
      "ordning": "6",
      "kandidatnummer": "25657"
    },
    {
      "valtyp": "KF",
      "område": "Tanum",
      "valkrets": "Tanum",
      "parti": "Moderaterna",
      "partiförkortning": "M",
      "ordning": "21",
      "kandidatnummer": "33105"
    },
    {
      "valtyp": "KF",
      "område": "Töreboda",
      "valkrets": "Töreboda",
      "parti": "Arbetarepartiet-Socialdemokraterna",
      "partiförkortning": "S",
      "ordning": "32",
      "kandidatnummer": "49009"
    },
    {
      "valtyp": "KF",
      "område": "Kristinehamn",
      "valkrets": "Kristinehamn",
      "parti": "Moderaterna",
      "partiförkortning": "M",
      "ordning": "13",
      "kandidatnummer": "31594"
    },
    {
      "valtyp": "KF",
      "område": "Malung-Sälen",
      "valkrets": "Malung-Sälen",
      "parti": "Moderaterna",
      "partiförkortning": "M",
      "ordning": "6",
      "kandidatnummer": "13239"
    },
    {
      "valtyp": "KF",
      "område": "Örnsköldsvik",
      "valkrets": "Örnsköldsviks Norra",
      "parti": "Sverigedemokraterna",
      "partiförkortning": "SD",
      "ordning": "2",
      "kandidatnummer": "31297"
    },
    {
      "valtyp": "KF",
      "område": "Örnsköldsvik",
      "valkrets": "Örnsköldsviks Södra",
      "parti": "Sverigedemokraterna",
      "partiförkortning": "SD",
      "ordning": "2",
      "kandidatnummer": "31297"
    }
  ]
}