{
  "namn": "Ulrika Spårebo",
  "kandidaturer": [
    {
      "valtyp": "RF",
      "område": "Västmanland",
      "valkrets": "Östra valkretsen",
      "parti": "Arbetarepartiet-Socialdemokraterna",
      "partiförkortning": "S",
      "ordning": "2",
      "kandidatnummer": "3693"
    },
    {
      "valtyp": "RF",
      "område": "Västmanland",
      "valkrets": "Östra valkretsen",
      "parti": "Arbetarepartiet-Socialdemokraterna",
      "partiförkortning": "S",
      "ordning": "2",
      "kandidatnummer": "3693"
    },
    {
      "valtyp": "RF",
      "område": "Västmanland",
      "valkrets": "Västra valkretsen",
      "parti": "Arbetarepartiet-Socialdemokraterna",
      "partiförkortning": "S",
      "ordning": "2",
      "kandidatnummer": "3693"
    },
    {
      "valtyp": "RF",
      "område": "Västmanland",
      "valkrets": "Västra valkretsen",
      "parti": "Arbetarepartiet-Socialdemokraterna",
      "partiförkortning": "S",
      "ordning": "2",
      "kandidatnummer": "3693"
    },
    {
      "valtyp": "KF",
      "område": "Sala",
      "valkrets": "Sala",
      "parti": "Arbetarepartiet-Socialdemokraterna",
      "partiförkortning": "S",
      "ordning": "27",
      "kandidatnummer": "3693"
    }
  ]
}